serieux/__init__.py
serieux/__main__.py
serieux/auto.py
serieux/ctx.py
serieux/docstrings.py
serieux/exc.py
serieux/impl.py
serieux/instructions.py
serieux/model.py
serieux/priority.py
serieux/py.typed
serieux/schema.py
serieux/tell.py
serieux/utils.py
serieux/version.py
serieux/features/__init__.py
serieux/features/autotag.py
serieux/features/clargs.py
serieux/features/comment.py
serieux/features/dotted.py
serieux/features/encrypt.py
serieux/features/fromfile.py
serieux/features/interpol.py
serieux/features/lazy.py
serieux/features/partial.py
serieux/features/prompt.py
serieux/features/proxy.py
serieux/features/registered.py
serieux/features/tagset.py
serieux/features/usermeth.py
serieux/formats/__init__.py
serieux/formats/abc.py
serieux/formats/json.py
serieux/formats/pkl.py
serieux/formats/toml.py
serieux/formats/txt.py
serieux/formats/yaml.py
serieux-0.3.4.dist-info/METADATA
serieux-0.3.4.dist-info/WHEEL
serieux-0.3.4.dist-info/entry_points.txt
serieux-0.3.4.dist-info/licenses/LICENSE
serieux-0.3.4.dist-info/RECORD
