Metadata-Version: 2.4
Name: serieux
Version: 0.3.4
Summary: Extremely customizable serialization
Project-URL: Homepage, https://serieux.readthedocs.io/en/latest/
Project-URL: Documentation, https://serieux.readthedocs.io/en/latest/
Project-URL: Repository, https://github.com/breuleux/serieux
Author-email: Olivier Breuleux <breuleux@gmail.com>
License-Expression: MIT
License-File: LICENSE
Requires-Python: >=3.11
Requires-Dist: ovld~=0.5.13
